appeau_client/__init__.py
appeau_client/api_calculdirect_post.py
appeau_client/api_date_calcul_parcelleId_get.py
appeau_client/api_donnees_meteomulti_post.py
appeau_client/api_parcelles_get_collection.py
appeau_client/api_parcelles_id_delete.py
appeau_client/api_parcelles_id_get.py
appeau_client/api_parcelles_id_patch.py
appeau_client/api_parcelles_parcelleIddonnees_meteo_dateDebut_dateFin_get_collection.py
appeau_client/api_parcelles_parcelleIdresultat_dateDebut_dateFin_get_collection.py
appeau_client/api_parcelles_post.py
appeau_client/api_parcellesattente_get_collection.py
appeau_client/api_parcellesdetails_get_collection.py
appeau_client/api_parcellesdetails_listParcellesId_get_collection.py
appeau_client/api_parcellesmulti_listParcellesIdresultat_dateDebut_dateFin_get_collection.py
appeau_client/login_check_post.py
appeau_client-0.2.0.dist-info/METADATA
appeau_client-0.2.0.dist-info/WHEEL
appeau_client-0.2.0.dist-info/top_level.txt
appeau_client-0.2.0.dist-info/RECORD
