Metadata-Version: 2.1
Name: appeau-client
Version: 0.2.0
Summary: A client for http://appeau.api.vignevin-epicure.com API
Author: Guilhem Heinrich
Author-email: guilhem.heinrich@id2l.fr
License: Apache 2.0
Requires-Dist: requests
